pylwr/__init__.py
pylwr/const.py
pylwr/distribute.py
pylwr/excel.py
pylwr/db/__init__.py
pylwr/db/database.py
pylwr/db/mysql.py
pylwr/db/oracle.py
pylwr/error/__init__.py
pylwr/error/error.py
pylwr/job/__init__.py
pylwr/job/transform.py
pylwr/log/__init__.py
pylwr/log/loguru.py
pylwr/micm/__init__.py
pylwr/micm/ka02.py
pylwr/micm/knowledge.py
pylwr/proxy/__init__.py
pylwr/proxy/portfind.py
pylwr/proxy/route.py
pylwr/proxy/v2ray.py
pylwr/proxy/v2ray_dell.py
pylwr/proxy/v2ray_wechat.py
pylwr/proxy/v2rayin.py
pylwr/proxy/v2rayshishi.py
pylwr-1.1.2.dist-info/LICENSE
pylwr-1.1.2.dist-info/METADATA
pylwr-1.1.2.dist-info/WHEEL
pylwr-1.1.2.dist-info/top_level.txt
pylwr-1.1.2.dist-info/RECORD
