Metadata-Version: 2.2
Name: pylwr
Version: 1.1.2
Summary: 各种包使用的二次封装
Home-page: https://gitee.com/linwanrui/pylwr
Author: linwr
Author-email: linwr <953297255@qq.com>
License: GPL-3.0-only
Project-URL: Homepage, https://gitee.com/linwanrui/pylwr
Project-URL: Bug Tracker, https://gitee.com/linwanrui/pylwr/issues
Classifier: Programming Language :: Python :: 3
Classifier: License :: OSI Approved :: GNU General Public License v3 (GPLv3)
Classifier: Operating System :: OS Independent
Requires-Python: >=3.10
License-File: LICENSE
Dynamic: author
Dynamic: home-page
